setup.py
mwdump/__init__.py
mwdump.egg-info/PKG-INFO
mwdump.egg-info/SOURCES.txt
mwdump.egg-info/dependency_links.txt
mwdump.egg-info/not-zip-safe
mwdump.egg-info/pbr.json
mwdump.egg-info/requires.txt
mwdump.egg-info/top_level.txt