Metadata-Version: 1.0
Name: mwdump
Version: 0.2
Summary: MediaWiki dump file reader
Home-page: https://github.com/cllu/mwdump
Author: Chunliang Lyu
Author-email: hi@chunlianglyu.com
License: MIT
Platform: UNKNOWN
